reqivo/__init__.py
reqivo/exceptions.py
reqivo/py.typed
reqivo/version.py
reqivo/client/__init__.py
reqivo/client/auth.py
reqivo/client/request.py
reqivo/client/response.py
reqivo/client/session.py
reqivo/client/websocket.py
reqivo/http/__init__.py
reqivo/http/body.py
reqivo/http/headers.py
reqivo/http/http11.py
reqivo/http/status_codes.py
reqivo/http/url.py
reqivo/server/__init__.py
reqivo/transport/__init__.py
reqivo/transport/connection.py
reqivo/transport/connection_pool.py
reqivo/transport/selectors.py
reqivo/transport/tls.py
reqivo/utils/__init__.py
reqivo/utils/serialization.py
reqivo/utils/timing.py
reqivo/utils/validators.py
reqivo/utils/websocket_utils.py
reqivo-0.1.0.dist-info/licenses/LICENSE.md
reqivo-0.1.0.dist-info/METADATA
reqivo-0.1.0.dist-info/WHEEL
reqivo-0.1.0.dist-info/top_level.txt
reqivo-0.1.0.dist-info/RECORD
