Metadata-Version: 2.4
Name: Reqivo
Version: 0.1.0
Summary: A modern, async-first HTTP client library for Python
Author-email: Rodrigo Ezequiel Roldán <roldriel@gmail.com>
License: MIT License
Project-URL: repository, https://github.com/roldriel/reqivo
Project-URL: documentation, https://roldriel.github.io/reqivo/
Project-URL: Bug Tracker, https://github.com/roldriel/reqivo/issues
Keywords: http,client,async,request,api
Classifier: Development Status :: 3 - Alpha
Classifier: Intended Audience :: Developers
Classifier: Operating System :: OS Independent
Classifier: Programming Language :: Python
Classifier: Programming Language :: Python :: 3
Classifier: Programming Language :: Python :: 3.9
Classifier: Programming Language :: Python :: 3.10
Classifier: Programming Language :: Python :: 3.11
Classifier: Programming Language :: Python :: 3.12
Classifier: Topic :: Internet :: WWW/HTTP
Classifier: Topic :: Software Development :: Libraries :: Python Modules
Classifier: Typing :: Typed
Requires-Python: >=3.9
License-File: LICENSE.md
Provides-Extra: docs
Requires-Dist: sphinx; extra == "docs"
Requires-Dist: myst-parser; extra == "docs"
Provides-Extra: test
Requires-Dist: pytest; extra == "test"
Requires-Dist: coverage; extra == "test"
Requires-Dist: pytest-asyncio; extra == "test"
Dynamic: license-file
